pytest_envraw/__init__.py
pytest_envraw/plugin.py
pytest_envraw-0.1.1.dist-info/LICENSE
pytest_envraw-0.1.1.dist-info/METADATA
pytest_envraw-0.1.1.dist-info/WHEEL
pytest_envraw-0.1.1.dist-info/entry_points.txt
pytest_envraw-0.1.1.dist-info/top_level.txt
pytest_envraw-0.1.1.dist-info/RECORD
