Metadata-Version: 2.1
Name: pytest-envraw
Version: 0.1.1
Summary: py.test plugin that allows you to add environment variables.
Home-page: https://github.com/Vegasq/pytest-env-raw
Author: mail@mkla.dev
Author-email: mail@mkla.dev
License: UNKNOWN
Platform: UNKNOWN
Classifier: Development Status :: 4 - Beta
Classifier: Intended Audience :: Developers
Classifier: License :: OSI Approved :: MIT License
Classifier: Natural Language :: English
Classifier: Programming Language :: Python :: 2
Classifier: Programming Language :: Python :: 2.6
Classifier: Programming Language :: Python :: 2.7
Classifier: Programming Language :: Python :: 3
Classifier: Programming Language :: Python :: 3.3
Requires-Dist: pytest (>=2.6.0)
